InSTAnT/InSTAnT.py
InSTAnT/__init__.py
InSTAnT/poibin.py
InSTAnT/poisson_binomial.py
InSTAnT/gspan_mining/__init__.py
InSTAnT/gspan_mining/__main__.py
InSTAnT/gspan_mining/config.py
InSTAnT/gspan_mining/graph.py
InSTAnT/gspan_mining/gspan.py
InSTAnT/gspan_mining/main.py
sc_instant-1.2.1.dist-info/LICENSE.txt
sc_instant-1.2.1.dist-info/METADATA
sc_instant-1.2.1.dist-info/WHEEL
sc_instant-1.2.1.dist-info/top_level.txt
sc_instant-1.2.1.dist-info/RECORD
