Metadata-Version: 2.1
Name: sc-instant
Version: 1.2.1
Summary: InSTAnT is a toolkit to identify gene pairs which are d-colocalized from single molecule measurement data.
Home-page: https://github.com/anurendra, https://github.com/Chokerino
Author: Anurendra Kumar, Bhavay Aggarwal
Author-email: anu.ankesh@gmail.com, bhavayaggarwal07@gmail.com
License: MIT
Keywords: InSTAnT,Python
Classifier: Development Status :: 3 - Alpha
Classifier: Intended Audience :: Developers
Classifier: Topic :: Software Development :: Build Tools
Classifier: License :: OSI Approved :: MIT License
Classifier: Programming Language :: Python :: 3
Classifier: Programming Language :: Python :: 3.4
Classifier: Programming Language :: Python :: 3.5
Classifier: Programming Language :: Python :: 3.6
License-File: LICENSE.txt
Requires-Dist: contourpy >=1.1.1
Requires-Dist: cycler >=0.12.1
Requires-Dist: et-xmlfile >=1.1.0
Requires-Dist: fonttools >=4.43.1
Requires-Dist: joblib >=1.3.2
Requires-Dist: kiwisolver >=1.4.5
Requires-Dist: matplotlib >=3.8.0
Requires-Dist: openpyxl >=3.1.2
Requires-Dist: packaging >=23.2
Requires-Dist: pillow >=10.1.0
Requires-Dist: psutil >=5.9.6
Requires-Dist: pyparsing >=3.1.1
Requires-Dist: scikit-learn >=1.3.2
Requires-Dist: scipy >=1.11.3
Requires-Dist: threadpoolctl >=3.2.0
Requires-Dist: pandas >=2.1.4
Requires-Dist: anndata >=0.10.4
Requires-Dist: networkx >=3.2.1
